essmc2/__init__.py
essmc2/version.py
essmc2/apis/__init__.py
essmc2/apis/_standard_test_config.py
essmc2/apis/_standard_train_config.py
essmc2/apis/config.py
essmc2/apis/data.py
essmc2/apis/model.py
essmc2/datasets/__init__.py
essmc2/datasets/base_dataset.py
essmc2/datasets/concat_dataset.py
essmc2/datasets/dataset_repeater.py
essmc2/datasets/image_classify_json_dataset.py
essmc2/datasets/registry.py
essmc2/datasets/videos/__init__.py
essmc2/datasets/videos/base_video_dataset.py
essmc2/datasets/videos/hmdb51.py
essmc2/datasets/videos/ssv2.py
essmc2/datasets/videos/ucf101.py
essmc2/hooks/__init__.py
essmc2/hooks/backward.py
essmc2/hooks/checkpoint.py
essmc2/hooks/hook.py
essmc2/hooks/log.py
essmc2/hooks/lr.py
essmc2/hooks/registry.py
essmc2/hooks/sampler.py
essmc2/hooks/tensorboard.py
essmc2/lr_schedulers/__init__.py
essmc2/lr_schedulers/registry.py
essmc2/models/__init__.py
essmc2/models/registry.py
essmc2/models/backbones/__init__.py
essmc2/models/backbones/image/__init__.py
essmc2/models/backbones/image/inceptionresnetv2.py
essmc2/models/backbones/image/inceptionresnetv2_impl.py
essmc2/models/backbones/image/resnet.py
essmc2/models/backbones/image/resnet_impl.py
essmc2/models/backbones/video/__init__.py
essmc2/models/backbones/video/init_helper.py
essmc2/models/backbones/video/resnet_3d.py
essmc2/models/backbones/video/video_transformer.py
essmc2/models/backbones/video/bricks/__init__.py
essmc2/models/backbones/video/bricks/base_branch.py
essmc2/models/backbones/video/bricks/csn_branch.py
essmc2/models/backbones/video/bricks/non_local.py
essmc2/models/backbones/video/bricks/r2d3d_branch.py
essmc2/models/backbones/video/bricks/r2plus1d_branch.py
essmc2/models/backbones/video/bricks/tada_conv.py
essmc2/models/backbones/video/bricks/transformer_branch.py
essmc2/models/backbones/video/bricks/visualize_3d_module.py
essmc2/models/backbones/video/bricks/stems/__init__.py
essmc2/models/backbones/video/bricks/stems/base_2d_stem.py
essmc2-0.1.4.dist-info/LICENSE
essmc2-0.1.4.dist-info/METADATA
essmc2-0.1.4.dist-info/WHEEL
essmc2-0.1.4.dist-info/top_level.txt
essmc2-0.1.4.dist-info/RECORD
