Metadata-Version: 2.1
Name: essmc2
Version: 0.1.4
Summary: EssentialMC2: A Video Understanding Algorithm Framework.
Home-page: https://github.com/alibaba/EssentialMC2
Author: Alibaba Damo Academy
Author-email: logistic1994@gmail.com
License: UNKNOWN
Keywords: compute vision,video,framework
Platform: UNKNOWN
Classifier: Programming Language :: Python :: 3
Classifier: Programming Language :: Python :: 3.6
Classifier: Programming Language :: Python :: 3.7
Classifier: Programming Language :: Python :: 3.8
Classifier: Programming Language :: Python :: 3.9
Classifier: License :: OSI Approved :: MIT License
Classifier: Operating System :: OS Independent
Requires-Python: >=3.6
Requires-Dist: addict (==2.4.0)
Requires-Dist: yapf (==0.32.0)
Requires-Dist: numpy
Requires-Dist: opencv-transforms (==0.0.6)
Requires-Dist: packaging (==21.0)
Requires-Dist: oss2 (>=2.13.1)
Requires-Dist: opencv-python (>=4.1.0)
Requires-Dist: einops (>=0.3.2)
Requires-Dist: docstring-parser (==0.14.1)
